{"cameraMode":{"drawMode":0,"name":"Shaded","section":"Shading Mode"},"sceneLighting":true,"audioPlay":false,"sceneViewState":{"m_AlwaysRefresh":false,"showFog":true,"showSkybox":true,"showFlares":true,"showImageEffects":true,"showParticleSystems":true,"showVisualEffectGraphs":true,"m_FxEnabled":true},"in2DMode":false,"pivot":{"x":-54.7237548828125,"y":20.114612579345704,"z":-58.208255767822269},"rotation":{"x":0.042979031801223758,"y":-0.5228792428970337,"z":0.027501946315169336,"w":0.8514248728752136},"size":3.5390877723693849,"orthographic":false}